pyatmos/__init__.py
pyatmos/class_atmos.py
pyatmos/data/.DS_Store
pyatmos/data/coesa76_coeffs.npz
pyatmos/data/nrlmsis00_data.npz
pyatmos/data/readme.txt
pyatmos/jb2008/JB2008_subfunc.py
pyatmos/jb2008/__init__.py
pyatmos/jb2008/jb2008.py
pyatmos/jb2008/spaceweather.py
pyatmos/msise/__init__.py
pyatmos/msise/nrlmsise00.py
pyatmos/msise/nrlmsise00_subfunc.py
pyatmos/msise/spaceweather.py
pyatmos/standardatmos/__init__.py
pyatmos/standardatmos/coesa76.py
pyatmos/standardatmos/expo.py
pyatmos/standardatmos/ussa76.py
pyatmos/utils/Const.py
pyatmos/utils/__init__.py
pyatmos/utils/data_download.py
pyatmos/utils/data_prepare.py
pyatmos/utils/try_download.py
pyatmos/utils/utils.py
pyatmos-1.2.7.dist-info/LICENSE.txt
pyatmos-1.2.7.dist-info/METADATA
pyatmos-1.2.7.dist-info/WHEEL
pyatmos-1.2.7.dist-info/top_level.txt
pyatmos-1.2.7.dist-info/RECORD
