Metadata-Version: 2.1
Name: pyatmos
Version: 1.2.7
Summary: A package to estimate the vertical structure of atmosphere with various atmospheric density models
Home-page: https://github.com/lcx366/ATMOS
Author: Chunxiao Li
Author-email: lcx366@126.com
License: MIT
Keywords: coesa76,nrlmsise00,jb2008
Classifier: Development Status :: 4 - Beta
Classifier: Intended Audience :: Education
Classifier: Intended Audience :: Science/Research
Classifier: Programming Language :: Python :: 3.10
Classifier: Programming Language :: Python :: 3.11
Classifier: Programming Language :: Python :: 3.12
Classifier: License :: OSI Approved :: MIT License
Requires-Python: >=3.10
License-File: LICENSE.txt
Requires-Dist: scipy
Requires-Dist: numpy
Requires-Dist: numba
Requires-Dist: pandas
Requires-Dist: astropy
Requires-Dist: wget
